djaken/__init__.py
djaken/admin.py
djaken/apps.py
djaken/models.py
djaken/tests.py
djaken/urls.py
djaken/views.py
djaken/migrations/0001_initial.py
djaken/migrations/0002_expanded_images.py
djaken/migrations/__init__.py
djaken/static/djaken/css/all_notes.css
djaken/static/djaken/css/base.css
djaken/static/djaken/css/edit_note.css
djaken/static/djaken/css/fonts.css
djaken/static/djaken/css/login.css
djaken/static/djaken/css/unlock_note.css
djaken/static/djaken/css/view_note.css
djaken/static/djaken/fonts/roboto-mono-v5-latin-ext_latin-100.eot
djaken/static/djaken/fonts/roboto-mono-v5-latin-ext_latin-100.svg
djaken/static/djaken/fonts/roboto-mono-v5-latin-ext_latin-100.ttf
djaken/static/djaken/fonts/roboto-mono-v5-latin-ext_latin-100.woff
djaken/static/djaken/fonts/roboto-mono-v5-latin-ext_latin-100.woff2
djaken/static/djaken/fonts/roboto-mono-v5-latin-ext_latin-100italic.eot
djaken/static/djaken/fonts/roboto-mono-v5-latin-ext_latin-100italic.svg
djaken/static/djaken/fonts/roboto-mono-v5-latin-ext_latin-100italic.ttf
djaken/static/djaken/fonts/roboto-mono-v5-latin-ext_latin-100italic.woff
djaken/static/djaken/fonts/roboto-mono-v5-latin-ext_latin-100italic.woff2
djaken/static/djaken/fonts/roboto-mono-v5-latin-ext_latin-300.eot
djaken/static/djaken/fonts/roboto-mono-v5-latin-ext_latin-300.svg
djaken/static/djaken/fonts/roboto-mono-v5-latin-ext_latin-300.ttf
djaken/static/djaken/fonts/roboto-mono-v5-latin-ext_latin-300.woff
djaken/static/djaken/fonts/roboto-mono-v5-latin-ext_latin-300.woff2
djaken/static/djaken/fonts/roboto-mono-v5-latin-ext_latin-300italic.eot
djaken/static/djaken/fonts/roboto-mono-v5-latin-ext_latin-300italic.svg
djaken/static/djaken/fonts/roboto-mono-v5-latin-ext_latin-300italic.ttf
djaken/static/djaken/fonts/roboto-mono-v5-latin-ext_latin-300italic.woff
djaken/static/djaken/fonts/roboto-mono-v5-latin-ext_latin-300italic.woff2
djaken/static/djaken/fonts/roboto-mono-v5-latin-ext_latin-500.eot
django_djaken-2.0.2.dist-info/DESCRIPTION.rst
django_djaken-2.0.2.dist-info/METADATA
django_djaken-2.0.2.dist-info/RECORD
django_djaken-2.0.2.dist-info/WHEEL
django_djaken-2.0.2.dist-info/metadata.json
django_djaken-2.0.2.dist-info/top_level.txt
