Metadata-Version: 2.0
Name: django-djaken
Version: 2.0.2
Summary: Djaken is a complete web-based notes application for Django.
Home-page: https://github.com/ethoms/django-djaken/
Author: Euan Thoms
Author-email: euan@potensol.com
License: BSD License
Keywords: django notes markdown encrypt
Platform: UNKNOWN
Classifier: Environment :: Web Environment
Classifier: Framework :: Django
Classifier: Intended Audience :: Information Technology
Classifier: License :: OSI Approved :: BSD License
Classifier: Operating System :: OS Independent
Classifier: Programming Language :: Python
Classifier: Programming Language :: Python :: 3
Classifier: Programming Language :: Python :: 3.3
Classifier: Programming Language :: Python :: 3.4
Classifier: Programming Language :: Python :: 3.5
Classifier: Programming Language :: Python :: 3.6
Classifier: Programming Language :: Python :: 3.7
Classifier: Topic :: Internet :: WWW/HTTP
Classifier: Topic :: Internet :: WWW/HTTP :: Dynamic Content
Requires-Dist: Django (<2.0,>=1.9)
Requires-Dist: docutils (>=0.12)
Requires-Dist: pycrypto (>=2.6)
